dsa_builder/__init__.py
dsa_builder/graph.py
dsa_builder/graph_algorithms.py
dsa_builder/linked_list.py
dsa_builder/queue.py
dsa_builder/rich_print.py
dsa_builder/search.py
dsa_builder/sorting.py
dsa_builder/stack.py
dsa_builder-1.0.0.dist-info/WHEEL
dsa_builder-1.0.0.dist-info/entry_points.txt
dsa_builder-1.0.0.dist-info/METADATA
dsa_builder-1.0.0.dist-info/RECORD
