Metadata-Version: 2.3
Name: dsa-builder
Version: 1.0.0
Summary: A complete Python library for Data Structures, Algorithms, Graphs, Searching, Sorting & Utilities — beginner-friendly, production-ready.
Author-email: sarthakdongare8@gmail.com
License: MIT
Requires-Dist: rich>=14.2.0
Requires-Python: >=3.11
